[
  {
    "type": "clothes_adult",
    "label": "одяг для дорослих",
    "details": {
      "inputType": "text",
      "view": "введіть розмір",
      "required": true
    }
  },

  {
    "type": "clothes_child",
    "label": "одяг для дітей",
    "details": {
      "inputType": "text",
      "view": "введіть розмір",
      "required": false
    }
  },

  {
    "type": "food",
    "label": "їжа",
    "details": {
      "inputType": "text",
      "view": "введіть побажання",
      "required": false
    }
  },

  {
    "type": "children_food",
    "label": "дитяче харчування",
    "details": {
      "inputType": "text",
      "view": "введіть вид",
      "required": true
    }
  },

  {
    "type": "diapers",
    "label": "підгузки",
    "details": {
      "inputType": "text",
      "view": "введіть розмір",
      "required": true
    }
  },

  {
    "type": "hygiene",
    "label": "засоби гігієни",
    "details": {
      "inputType": "text",
      "view": "введіть вид",
      "required": false
    }
  },

  {
    "type": "otherHelp",
    "label": "інший тип допомоги",
    "details": {
      "inputType": "text",
      "view": "введіть вид",
      "required": true
    }
  }
]
